{
"companyName": "DefaultCompany",
"productName": "ComunityGameJam",
"productVersion": "0.1",
"dataUrl": "buildLiar.data.unityweb",
"wasmCodeUrl": "buildLiar.wasm.code.unityweb",
"wasmFrameworkUrl": "buildLiar.wasm.framework.unityweb",
"graphicsAPI": ["WebGL 2.0","WebGL 1.0"],
"webglContextAttributes": {"preserveDrawingBuffer": false},
"splashScreenStyle": "Dark",
"backgroundColor": "#231F20",
"cacheControl": {"default": "must-revalidate"},
"developmentBuild": false,
"multithreading": false,
"unityVersion": "2019.2.1f1"
}